drf_versioned_schemas/__init__.py
drf_versioned_schemas/apps.py
drf_versioned_schemas/models.py
drf_versioned_schemas/routers.py
drf_versioned_schemas/serializers.py
drf_versioned_schemas/viewsets.py
drf_versioned_schemas-0.1.1.dist-info/LICENSE
drf_versioned_schemas-0.1.1.dist-info/METADATA
drf_versioned_schemas-0.1.1.dist-info/WHEEL
drf_versioned_schemas-0.1.1.dist-info/top_level.txt
drf_versioned_schemas-0.1.1.dist-info/RECORD
